swordcloud/THSarabun.ttf
swordcloud/__init__.py
swordcloud/color_func.py
swordcloud/occupancy.py
swordcloud/processing.py
swordcloud/stopwords
swordcloud/thstopwords
swordcloud/tokenization.py
swordcloud/wordcloud.py
swordcloud-0.0.10.dist-info/METADATA
swordcloud-0.0.10.dist-info/WHEEL
swordcloud-0.0.10.dist-info/top_level.txt
swordcloud-0.0.10.dist-info/RECORD
