Metadata-Version: 2.1
Name: swordcloud
Version: 0.0.10
Summary: Semantic word cloud package for Thai and English
Author-email: Attapol Thamrongrattanarit <profte@gmail.com>
License: MIT
Project-URL: Homepage, https://github.com/nlp-chula/swordcloud
Keywords: python,word cloud,t-SNE,K-means
Classifier: Development Status :: 3 - Alpha
Classifier: Intended Audience :: Education
Classifier: Programming Language :: Python :: 3
Classifier: Operating System :: MacOS :: MacOS X
Classifier: Operating System :: Microsoft :: Windows
Requires-Python: >=3.8
Requires-Dist: numpy >=1.21.0
Requires-Dist: pillow
Requires-Dist: matplotlib >=1.5.3
Requires-Dist: gensim >=4.0.0
Requires-Dist: pandas
Requires-Dist: pythainlp >=3.1.0
Requires-Dist: k-means-constrained
Requires-Dist: scikit-learn
Provides-Extra: embedfont
Requires-Dist: fonttools ; extra == 'embedfont'
